odoo/addons/photovoltaic_api/CHANGELOG.md
odoo/addons/photovoltaic_api/__init__.py
odoo/addons/photovoltaic_api/__manifest__.py
odoo/addons/photovoltaic_api/cliff.toml
odoo/addons/photovoltaic_api/controllers/__init__.py
odoo/addons/photovoltaic_api/controllers/controller.py
odoo/addons/photovoltaic_api/data/contract.xml
odoo/addons/photovoltaic_api/data/data.xml
odoo/addons/photovoltaic_api/models/__init__.py
odoo/addons/photovoltaic_api/models/auth_jwt_validator.py
odoo/addons/photovoltaic_api/pydantic_models/__init__.py
odoo/addons/photovoltaic_api/pydantic_models/allocation.py
odoo/addons/photovoltaic_api/pydantic_models/bank_account.py
odoo/addons/photovoltaic_api/pydantic_models/contact.py
odoo/addons/photovoltaic_api/pydantic_models/contract.py
odoo/addons/photovoltaic_api/pydantic_models/info.py
odoo/addons/photovoltaic_api/pydantic_models/list_response.py
odoo/addons/photovoltaic_api/pydantic_models/metrics.py
odoo/addons/photovoltaic_api/pydantic_models/power_station.py
odoo/addons/photovoltaic_api/pydantic_models/power_station_production.py
odoo/addons/photovoltaic_api/pydantic_models/user.py
odoo/addons/photovoltaic_api/security/ir.model.access.csv
odoo/addons/photovoltaic_api/services/__init__.py
odoo/addons/photovoltaic_api/services/account.py
odoo/addons/photovoltaic_api/services/allocations.py
odoo/addons/photovoltaic_api/services/bank_account.py
odoo/addons/photovoltaic_api/services/contacts.py
odoo/addons/photovoltaic_api/services/contracts.py
odoo/addons/photovoltaic_api/services/info.py
odoo/addons/photovoltaic_api/services/powerstation.py
odoo/addons/photovoltaic_api/services/user.py
odoo/addons/photovoltaic_api/tests/__init__.py
odoo/addons/photovoltaic_api/tests/common.py
odoo/addons/photovoltaic_api/tests/test_account.py
odoo13_addon_photovoltaic_api-13.0.1.4.3.dist-info/METADATA
odoo13_addon_photovoltaic_api-13.0.1.4.3.dist-info/WHEEL
odoo13_addon_photovoltaic_api-13.0.1.4.3.dist-info/top_level.txt
odoo13_addon_photovoltaic_api-13.0.1.4.3.dist-info/RECORD
