Metadata-Version: 2.1
Name: odoo13-addon-photovoltaic_api
Version: 13.0.1.4.3
Requires-Python: >=3.5
Requires-Dist: odoo13-addon-auth_api_key
Requires-Dist: odoo13-addon-auth_jwt
Requires-Dist: odoo13-addon-base_rest
Requires-Dist: odoo13-addon-base_rest_pydantic
Requires-Dist: odoo13-addon-photovoltaic_mgmt_extended
Requires-Dist: odoo13-addon-pydantic
Requires-Dist: odoo>=13.0a,<13.1dev
Requires-Dist: pydantic[email]<2.0
Requires-Dist: pyjwt
Summary: Photovoltaic API
Author: Librecoop
Classifier: Programming Language :: Python
Classifier: Framework :: Odoo
Classifier: Framework :: Odoo :: 13.0
